catchpoint_configurator/__init__.py
catchpoint_configurator/api.py
catchpoint_configurator/cli.py
catchpoint_configurator/config.py
catchpoint_configurator/constants.py
catchpoint_configurator/contest.py
catchpoint_configurator/core.py
catchpoint_configurator/exceptions.py
catchpoint_configurator/logging.py
catchpoint_configurator/template.py
catchpoint_configurator/types.py
catchpoint_configurator/utils.py
catchpoint_configurator-0.1.0.dist-info/licenses/LICENSE
catchpoint_configurator-0.1.0.dist-info/METADATA
catchpoint_configurator-0.1.0.dist-info/WHEEL
catchpoint_configurator-0.1.0.dist-info/entry_points.txt
catchpoint_configurator-0.1.0.dist-info/top_level.txt
catchpoint_configurator-0.1.0.dist-info/RECORD
